rechord/__init__.py
rechord/cli.py
Rechord-1.3.0.dist-info/LICENSE
Rechord-1.3.0.dist-info/METADATA
Rechord-1.3.0.dist-info/WHEEL
Rechord-1.3.0.dist-info/entry_points.txt
Rechord-1.3.0.dist-info/top_level.txt
Rechord-1.3.0.dist-info/RECORD
