Metadata-Version: 2.1
Name: Rechord
Version: 1.3.0
Summary: A simple python script to generate chord charts.
Home-page: https://github.com/zfdavis/rechord
Author: Zach Davis
Author-email: zfdavis21@gmail.com
License: MIT
Platform: UNKNOWN
Classifier: Programming Language :: Python :: 3
Classifier: License :: OSI Approved :: MIT License
Classifier: Operating System :: OS Independent
Requires-Dist: Click
